neon/__init__.py
neon/decoder.py
neon/encoder.py
neon/entity.py
neon/errors.py
neon/tokens.py
neon/utils.py
neon/version.py
neon_py-0.2.1.dist-info/LICENSE
neon_py-0.2.1.dist-info/METADATA
neon_py-0.2.1.dist-info/WHEEL
neon_py-0.2.1.dist-info/top_level.txt
neon_py-0.2.1.dist-info/RECORD
