Metadata-Version: 2.1
Name: neon-py
Version: 0.2.1
Summary: NEON parser for Python
Author-email: Pavel Dedik <dedikx@gmail.com>
License: BSD
Project-URL: Homepage, https://github.com/paveldedik/neon-py
Keywords: neon,parser,config file
Classifier: Programming Language :: Python
Classifier: Operating System :: OS Independent
Classifier: Topic :: Utilities
Classifier: Programming Language :: Python :: 3
Classifier: Programming Language :: Python :: 3.7
Classifier: Programming Language :: Python :: 3.8
Classifier: Programming Language :: Python :: 3.9
License-File: LICENSE
Requires-Dist: python-dateutil
Requires-Dist: more-itertools
Provides-Extra: test
Requires-Dist: pytest ; extra == 'test'
Provides-Extra: testing
Requires-Dist: pytest ; extra == 'testing'
